HadoopTheDefinitiveGuide4eZhongwenban/README.md
HadoopTheDefinitiveGuide4eZhongwenban/__init__.py
HadoopTheDefinitiveGuide4eZhongwenban/__main__.py
HadoopTheDefinitiveGuide4eZhongwenban/file.epub
HadoopTheDefinitiveGuide4eZhongwenban/index.html
HadoopTheDefinitiveGuide4eZhongwenban/css/__init__.py
HadoopTheDefinitiveGuide4eZhongwenban/css/annotations.css
HadoopTheDefinitiveGuide4eZhongwenban/css/main.css
HadoopTheDefinitiveGuide4eZhongwenban/css/normalize.css
HadoopTheDefinitiveGuide4eZhongwenban/css/popup.css
HadoopTheDefinitiveGuide4eZhongwenban/font/__init__.py
HadoopTheDefinitiveGuide4eZhongwenban/font/fontello.eot
HadoopTheDefinitiveGuide4eZhongwenban/font/fontello.svg
HadoopTheDefinitiveGuide4eZhongwenban/font/fontello.ttf
HadoopTheDefinitiveGuide4eZhongwenban/font/fontello.woff
HadoopTheDefinitiveGuide4eZhongwenban/img/__init__.py
HadoopTheDefinitiveGuide4eZhongwenban/img/annotator-glyph-sprite.png
HadoopTheDefinitiveGuide4eZhongwenban/img/annotator-icon-sprite.png
HadoopTheDefinitiveGuide4eZhongwenban/img/apple-touch-icon.png
HadoopTheDefinitiveGuide4eZhongwenban/img/cancelfullscreen.png
HadoopTheDefinitiveGuide4eZhongwenban/img/close.png
HadoopTheDefinitiveGuide4eZhongwenban/img/fullscreen.png
HadoopTheDefinitiveGuide4eZhongwenban/img/loader.gif
HadoopTheDefinitiveGuide4eZhongwenban/img/menu-icon.png
HadoopTheDefinitiveGuide4eZhongwenban/img/save.png
HadoopTheDefinitiveGuide4eZhongwenban/img/saved.png
HadoopTheDefinitiveGuide4eZhongwenban/img/settings-s.png
HadoopTheDefinitiveGuide4eZhongwenban/img/settings.png
HadoopTheDefinitiveGuide4eZhongwenban/img/star.png
HadoopTheDefinitiveGuide4eZhongwenban/js/__init__.py
HadoopTheDefinitiveGuide4eZhongwenban/js/epub.js
HadoopTheDefinitiveGuide4eZhongwenban/js/epub.min.js
HadoopTheDefinitiveGuide4eZhongwenban/js/epub.min.map
HadoopTheDefinitiveGuide4eZhongwenban/js/hooks.min.js
HadoopTheDefinitiveGuide4eZhongwenban/js/hooks.min.map
HadoopTheDefinitiveGuide4eZhongwenban/js/reader.js
hadoop_the_definitive_guide_4e_zhongwenban-2024.3.4.0.dist-info/METADATA
hadoop_the_definitive_guide_4e_zhongwenban-2024.3.4.0.dist-info/WHEEL
hadoop_the_definitive_guide_4e_zhongwenban-2024.3.4.0.dist-info/entry_points.txt
hadoop_the_definitive_guide_4e_zhongwenban-2024.3.4.0.dist-info/top_level.txt
hadoop_the_definitive_guide_4e_zhongwenban-2024.3.4.0.dist-info/RECORD
